tgcf/__init__.py
tgcf/bot/__init__.py
tgcf/bot/live_bot.py
tgcf/bot/utils.py
tgcf/cli.py
tgcf/config.py
tgcf/const.py
tgcf/live.py
tgcf/past.py
tgcf/plugin_models.py
tgcf/plugins/__init__.py
tgcf/plugins/caption.py
tgcf/plugins/filter.py
tgcf/plugins/fmt.py
tgcf/plugins/mark.py
tgcf/plugins/ocr.py
tgcf/plugins/replace.py
tgcf/storage.py
tgcf/utils.py
tgcf/web_ui/0_👋_Hello.py
tgcf/web_ui/pages/1_🔑_Telegram_Login.py
tgcf/web_ui/pages/2_⭐_Admins.py
tgcf/web_ui/pages/3_🔗_Connections.py
tgcf/web_ui/pages/4_🔌_Plugins.py
tgcf/web_ui/pages/5_🏃_Run.py
tgcf/web_ui/pages/6_🔬_Advanced.py
tgcf/web_ui/password.py
tgcf/web_ui/run.py
tgcf/web_ui/utils.py
tgcf-1.1.8.dist-info/entry_points.txt
tgcf-1.1.8.dist-info/LICENSE
tgcf-1.1.8.dist-info/WHEEL
tgcf-1.1.8.dist-info/METADATA
tgcf-1.1.8.dist-info/RECORD
